pwmProject_v3/code/spi_slave .v

`timescale 1ns / 1ps

module spi_slave #(

  parameter CPOL   = 1'b0,  // When one, polarity is low, otherwise polarity is high (Type - Boolean, Default value = 1'b0, Min value = 1'b0, Max value = 1'b1)
  parameter CPHA   = 1'b0,  // When one, sampling occurs at falling edge, otherwise at rising edge of non-inverted clock (Type - Boolean, Default value = 1'b0, Min value = 1'b0, Max value = 1'b1)
  parameter WIDTH  = 8,     // The width of the input and output data buses (Type - Decimal, Default value = 8, Min value = 8, Max value = 64)
  parameter LSB    = 1'b0   // When one, data starts from LSB, otherwise data starts from MSB (Type - Boolean, Default value = 1'b0, Min value = 1'b0, Max value = 1'b1)
) (
// common port
  input                  i_clk,         // input clock domain signal
  input                  i_rst,         // input reset signal
// interface port
  input                  i_sck,         // input spi clock signal
  input                  i_mosi,        // input master output slave input signal
  input                  i_ss_n,        // input slave select signal
  output reg             o_miso,        // output master input slave output signal
  output reg             o_miso_oe,     // output miso enable output signal
// internal port
  input                  i_reset,       // input registers initialization signal
  input      [WIDTH-1:0] i_tx_data,     // input data bus
  output reg             o_tx_int,      // output data transfer load interrupt signal

  output reg             o_rx_int,      // output data receive interrupt signal
  output reg [WIDTH-1:0] o_rx_data      // output data bus
);

  reg         [WIDTH-1:0] r_shift_miso;
  reg         [WIDTH-1:0] r_shift_mosi;
  reg [$clog2(WIDTH)-1:0] r_rx_counter;

  reg [1:0] r_ss_n_old;
  reg [1:0] r_sck_old;

  // Slave select negative synchronizer
  always @(posedge i_clk) begin
    if (i_rst)
      r_ss_n_old <= 2'b11;
    else begin
      r_ss_n_old[0] <= i_ss_n;
      r_ss_n_old[1] <= r_ss_n_old[0];
    end

  end

  // SPI clock negative synchronizer
  always @(posedge i_clk) begin
    if (i_rst)
      r_sck_old <= 2'b00;
    else begin
      r_sck_old[0] <= i_sck;
      r_sck_old[1] <= r_sck_old[0];
    end
  end

  // SPI data receiver
  always @(posedge i_clk) begin
    if (i_rst) begin
      r_rx_counter <= 'h00;
      r_shift_mosi <= 'h00;
      o_rx_int     <= 1'b0;
      o_rx_data    <= 'h00;
    end else if (i_reset) begin
      r_rx_counter <= 'h00;

      r_shift_mosi <= 'h00;
      o_rx_int     <= 1'b0;
      o_rx_data    <= 'h00;
    end else if (r_ss_n_old == 2'b11) begin
      r_rx_counter <= 'h00;
      r_shift_mosi <= 'h00;
      o_rx_int     <= 1'b0;
    end else if (r_ss_n_old == 2'b00) begin
      if ((CPOL ^ CPHA) == 1) begin
        if (r_sck_old == 2'b10) begin
          r_shift_mosi   <= {r_shift_mosi[WIDTH-2:0], i_mosi};
          if (r_rx_counter == WIDTH - 1) begin
            r_rx_counter <= 'h0;
            o_rx_data    <= {r_shift_mosi[WIDTH-2:0], i_mosi};
            o_rx_int     <= 1'b1;
          end else begin
            r_rx_counter <= r_rx_counter + 1;
            o_rx_int     <= 1'b0;
          end

        end
      end else if ((CPOL ^ CPHA) == 0) begin
        if (r_sck_old == 2'b01) begin
          r_shift_mosi   <= {r_shift_mosi[WIDTH-2:0], i_mosi};
          if (r_rx_counter == WIDTH - 1) begin
            r_rx_counter <= 'h0;
            o_rx_data    <= {r_shift_mosi[WIDTH-2:0], i_mosi};
            o_rx_int     <= 1'b1;
          end else begin
            r_rx_counter <= r_rx_counter + 1;
            o_rx_int     <= 1'b0;
          end
        end
      end
    end
  end

  // SPI data transmitter
  always @(posedge i_clk) begin

    if (i_rst) begin
      o_tx_int     <= 1'b0;
      o_miso       <= 1'b0;
      o_miso_oe    <= 1'b0;
      r_shift_miso <= 'h00;
    end else if (i_reset) begin
      o_tx_int     <= 1'b0;
      o_miso       <= 1'b0;
      o_miso_oe    <= 1'b0;
      r_shift_miso <= 'h00;
    end else if (r_ss_n_old == 2'b11) begin
      o_tx_int     <= 1'b0;
      o_miso       <= 1'b0;
      o_miso_oe    <= 1'b0;
      r_shift_miso <= 'h00;
    end else if (r_ss_n_old == 2'b10) begin
      r_shift_miso <= i_tx_data;
      o_tx_int     <= 1'b1;
      o_miso_oe    <= 1'b1;
      if (LSB) begin
        o_miso     <= i_tx_data[0];

      end else begin
        o_miso     <= i_tx_data[WIDTH-1];
      end
    end else if (r_ss_n_old == 2'b00) begin
      o_miso_oe    <= 1'b1;
      if ((CPOL ^ CPHA) == 1) begin
        if (r_sck_old == 2'b01) begin
          o_tx_int <= 1'b0;
          if (LSB) begin
            o_miso <= r_shift_miso[r_rx_counter];
          end else begin
            o_miso <= r_shift_miso[(WIDTH-1) - r_rx_counter];
          end
        end
      end else begin
        if (r_sck_old == 2'b10) begin
          o_tx_int <= 1'b0;
          if (LSB) begin
            o_miso <= 

r_shift_miso[r_rx_counter];
          end else begin
            o_miso <= r_shift_miso[(WIDTH-1) - r_rx_counter];
          end
        end
      end
    end
  end

endmodule

projectPWM_solution/code/project_1/project_1.srcs/sources_1/imports/code/spi_slave_tb.v

`timescale 1ns / 1ps

module spi_slave_tb();
  localparam CLK_PER     = 10;
  localparam CLK_SPI_PER = 100;

  integer i              = 0;
//Parameters
  parameter CPOL  = 1'b0;
  parameter CPHA  = 1'b0;
  parameter WIDTH = 8;
  parameter LSB   = 1'b0;
//Inputs
  reg              r_clk     = 1'b0;
  reg              r_rst     = 1'b1;
  reg              r_sck     = 1'b0;
  reg              r_mosi    = 1'b0;
  reg              r_ss_n    = 1'b0;
  reg              r_reset   = 1'b0;
  reg [WIDTH-1:0]  r_tx_data = 'h0000;
//Outputs
  wire             w_miso;
  wire             w_miso_oe;
  wire [WIDTH-1:0] w_rx_data;
  wire             w_tx_int;
  wire             w_rx_int;

// Module SPI slave (Serial Peripheral Interface) is a 4-wire synchronous serial communication interface.
  spi_slave #(
    .CPOL  (CPOL ),
    .CPHA  (CPHA ),
    .WIDTH (WIDTH),
    .LSB   (LSB  )
  ) dut (
    .i_clk     (r_clk    ),
    .i_rst     (r_rst    ),
    .i_sck     (r_sck    ),
    .i_mosi    (r_mosi   ),
    .i_ss_n    (r_ss_n   ),
    .o_miso    (w_miso   ),
    .o_miso_oe (w_miso_oe),
    .i_reset   (r_reset  ),
    .i_tx_data (r_tx_data),
    .o_tx_int  (w_tx_int ),
    .o_rx_int  (w_rx_int ),
    .o_rx_data (w_rx_data)

  );

  always #(CLK_PER/2)
    r_clk <= ~r_clk;

  // Task generate data for test receiver
  task receive_send_data;
    input [WIDTH-1:0] i_data_rx;
    begin
      if ((CPOL ^ CPHA) == 1) begin
        if (r_sck == 0) begin
          r_sck <= 1'b1;
        end
        #CLK_SPI_PER;
      end else begin
        if (r_sck == 1) begin
          r_sck <= 1'b0;
        end
        #CLK_SPI_PER;
      end
      for (i = 0; i <= WIDTH - 1; i = i + 1) begin

        r_mosi = i_data_rx[WIDTH-1 - i];
        if ((CPOL ^ CPHA) == 1) begin
          #CLK_SPI_PER r_sck <= 1'b0;
          #CLK_SPI_PER r_sck <= 1'b1;
        end else begin
          #CLK_SPI_PER r_sck <= 1'b1;
          #CLK_SPI_PER r_sck <= 1'b0;
        end
        if (i == WIDTH-1)
        r_mosi <= 1'b0;
      end
    end
  endtask

  // Task generate data for test transmitter
  task load_tx_data;
    input [WIDTH-1:0] i_data_tx;
    begin
      if (r_ss_n == 0) begin
        #CLK_SPI_PER r_ss_n  <= 1'b1;
      end

      #CLK_SPI_PER r_tx_data <= i_data_tx;
      #CLK_SPI_PER r_ss_n    <= 1'b0;
      #CLK_SPI_PER;
    end
  endtask

  initial begin
    $dumpfile("spi_slave_tb.vcd");
    $dumpvars(0, spi_slave_tb);

    r_clk        <= 1'b0;
    r_sck        <= 1'b0;
    r_reset      <= 1'b1;
    r_rst        <= 1'b1;
    r_mosi       <= 1'b0;
    r_ss_n       <= 1'b0;
    r_tx_data    <= 'h00;
    #100 r_rst   <= 1'b0;
    #100 r_reset <= 1'b0;

    receive_send_data('hAFCD);

    #100 r_reset <= 1'b1;
    #100 r_reset <= 1'b0;

    load_tx_data('hDE6A);
    receive_send_data('h0000);
    #100 r_reset <= 1'b1;
    #100 r_reset <= 1'b0;

    load_tx_data('h4EFB);
    receive_send_data('h6C8E);
    #100 r_reset <= 1'b1;
    #100 r_reset <= 1'b0;

    load_tx_data('hFE3A);
    receive_send_data('h6C8E);
    receive_send_data('h6C8E);

    #100 r_reset <= 1'b1;
    #100 r_reset <= 1'b0;

    #100 $finish;

  end

endmodule

projectPWM_solution/code/project_1/project_1.sim/sim_1/behav/xsim/spi_slave_tb.vcd
$date
   Fri Aug  9 09:45:04 2024
$end

$version
  2023.2
  $dumpfile ("spi_slave_tb.vcd") 
$end

$timescale
  1ps
$end

$scope module spi_slave_tb $end
$var integer 32 ! i [31:0] $end
$var reg 1 " r_clk $end
$var reg 1 # r_rst $end
$var reg 1 $ r_sck $end
$var reg 1 % r_mosi $end
$var reg 1 & r_ss_n $end
$var reg 1 ' r_reset $end
$var reg 8 ( r_tx_data [7:0] $end
$var wire 1 ) w_miso $end
$var wire 1 * w_miso_oe $end
$var wire 8 + w_rx_data [7:0] $end
$var wire 1 , w_tx_int $end
$var wire 1 - w_rx_int $end
$scope module dut $end
$var wire 1 . i_clk $end
$var wire 1 / i_rst $end
$var wire 1 0 i_sck $end
$var wire 1 1 i_mosi $end
$var wire 1 2 i_ss_n $end
$var reg 1 3 o_miso $end
$var reg 1 4 o_miso_oe $end
$var wire 1 5 i_reset $end
$var wire 8 6 i_tx_data [7:0] $end
$var reg 1 7 o_tx_int $end
$var reg 1 8 o_rx_int $end
$var reg 8 9 o_rx_data [7:0] $end
$var reg 8 : r_shift_miso [7:0] $end
$var reg 8 ; r_shift_mosi [7:0] $end
$var reg 3 < r_rx_counter [2:0] $end
$var reg 2 = r_ss_n_old [1:0] $end
$var reg 2 > r_sck_old [1:0] $end
$upscope $end
$scope task receive_send_data $end
$var reg 8 ? i_data_rx [7:0] $end
$upscope $end
$scope task load_tx_data $end
$var reg 8 @ i_data_tx [7:0] $end
$upscope $end
$upscope $end
$enddefinitions $end

#0
$dumpvars
b0 !
0"
1#
0$
0%
0&
1'
b0 (
x)
x*
bx +
x,
x-
0.
1/
00
01
02
x3
x4
15
b0 6
x7
x8
bx 9
bx :
bx ;
bx <
bx =
bx >
bx ?
bx @
$end

#5000
1"
0)
0*
b0 +
0,
0-
1.
03
04
07
08
b0 9
b0 :
b0 ;
b0 <
b11 =
b0 >

#10000
0"
0.

#15000
1"
1.

#20000
0"
0.

#25000
1"
1.

#30000
0"
0.

#35000
1"
1.

#40000
0"
0.

#45000
1"
1.

#50000
0"
0.

#55000
1"
1.

#60000
0"
0.

#65000
1"
1.

#70000
0"
0.

#75000
1"
1.

#80000
0"
0.

#85000
1"
1.

#90000
0"
0.

#95000
1"
1.

#100000
0"
0#
0.
0/

#105000
1"
1.
b10 =

#110000
0"
0.

#115000
1"
1.
b0 =

#120000
0"
0.

#125000
1"
1.

#130000
0"
0.

#135000
1"
1.

#140000
0"
0.

#145000
1"
1.

#150000
0"
0.

#155000
1"
1.

#160000
0"
0.

#165000
1"
1.

#170000
0"
0.

#175000
1"
1.

#180000
0"
0.

#185000
1"
1.

#190000
0"
0.

#195000
1"
1.

#200000
0"
0'
0.
05
b11001101 ?

#205000
1"
1*
1.
14

#210000
0"
0.

#215000
1"
1.

#220000
0"
0.

#225000
1"
1.

#230000
0"
0.

#235000
1"
1.

#240000
0"
0.

#245000
1"
1.

#250000
0"
0.

#255000
1"
1.

#260000
0"
0.

#265000
1"
1.

#270000
0"
0.

#275000
1"
1.

#280000
0"
0.

#285000
1"
1.

#290000
0"
0.

#295000
1"
1.

#300000
0"
1%
0.
11

#305000
1"
1.

#310000
0"
0.

#315000
1"
1.

#320000
0"
0.

#325000
1"
1.

#330000
0"
0.

#335000
1"
1.

#340000
0"
0.

#345000
1"
1.

#350000
0"
0.

#355000
1"
1.

#360000
0"
0.

#365000
1"
1.

#370000
0"
0.

#375000
1"
1.

#380000
0"
0.

#385000
1"
1.

#390000
0"
0.

#395000
1"
1.

#400000
0"
1$
0.
10

#405000
1"
1.
b1 >

#410000
0"
0.

#415000
1"
1.
b1 ;
b1 <
b11 >

#420000
0"
0.

#425000
1"
1.

#430000
0"
0.

#435000
1"
1.

#440000
0"
0.

#445000
1"
1.

#450000
0"
0.

#455000
1"
1.

#460000
0"
0.

#465000
1"
1.

#470000
0"
0.

#475000
1"
1.

#480000
0"
0.

#485000
1"
1.

#490000
0"
0.

#495000
1"
1.

#500000
b1 !
0"
0$
0.
00

#505000
1"
1.
b10 >

#510000
0"
0.

#515000
1"
1.
b0 >

#520000
0"
0.

#525000
1"
1.

#530000
0"
0.

#535000
1"
1.

#540000
0"
0.

#545000
1"
1.

#550000
0"
0.

#555000
1"
1.

#560000
0"
0.

#565000
1"
1.

#570000
0"
0.

#575000
1"
1.

#580000
0"
0.

#585000
1"
1.

#590000
0"
0.

#595000
1"
1.

#600000
0"
1$
0.
10

#605000
1"
1.
b1 >

#610000
0"
0.

#615000
1"
1.
b11 ;
b10 <
b11 >

#620000
0"
0.

#625000
1"
1.

#630000
0"
0.

#635000
1"
1.

#640000
0"
0.

#645000
1"
1.

#650000
0"
0.

#655000
1"
1.

#660000
0"
0.

#665000
1"
1.

#670000
0"
0.

#675000
1"
1.

#680000
0"
0.

#685000
1"
1.

#690000
0"
0.

#695000
1"
1.

#700000
b10 !
0"
0$
0%
0.
00
01

#705000
1"
1.
b10 >

#710000
0"
0.

#715000
1"
1.
b0 >

#720000
0"
0.

#725000
1"
1.

#730000
0"
0.

#735000
1"
1.

#740000
0"
0.

#745000
1"
1.

#750000
0"
0.

#755000
1"
1.

#760000
0"
0.

#765000
1"
1.

#770000
0"
0.

#775000
1"
1.

#780000
0"
0.

#785000
1"
1.

#790000
0"
0.

#795000
1"
1.

#800000
0"
1$
0.
10

#805000
1"
1.
b1 >

#810000
0"
0.

#815000
1"
1.
b110 ;
b11 <
b11 >

#820000
0"
0.

#825000
1"
1.

#830000
0"
0.

#835000
1"
1.

#840000
0"
0.

#845000
1"
1.

#850000
0"
0.

#855000
1"
1.

#860000
0"
0.

#865000
1"
1.

#870000
0"
0.

#875000
1"
1.

#880000
0"
0.

#885000
1"
1.

#890000
0"
0.

#895000
1"
1.

#900000
b11 !
0"
0$
0.
00

#905000
1"
1.
b10 >

#910000
0"
0.

#915000
1"
1.
b0 >

#920000
0"
0.

#925000
1"
1.

#930000
0"
0.

#935000
1"
1.

#940000
0"
0.

#945000
1"
1.

#950000
0"
0.

#955000
1"
1.

#960000
0"
0.

#965000
1"
1.

#970000
0"
0.

#975000
1"
1.

#980000
0"
0.

#985000
1"
1.

#990000
0"
0.

#995000
1"
1.

#1000000
0"
1$
0.
10

#1005000
1"
1.
b1 >

#1010000
0"
0.

#1015000
1"
1.
b1100 ;
b100 <
b11 >

#1020000
0"
0.

#1025000
1"
1.

#1030000
0"
0.

#1035000
1"
1.

#1040000
0"
0.

#1045000
1"
1.

#1050000
0"
0.

#1055000
1"
1.

#1060000
0"
0.

#1065000
1"
1.

#1070000
0"
0.

#1075000
1"
1.

#1080000
0"
0.

#1085000
1"
1.

#1090000
0"
0.

#1095000
1"
1.

#1100000
b100 !
0"
0$
1%
0.
00
11

#1105000
1"
1.
b10 >

#1110000
0"
0.

#1115000
1"
1.
b0 >

#1120000
0"
0.

#1125000
1"
1.

#1130000
0"
0.

#1135000
1"
1.

#1140000
0"
0.

#1145000
1"
1.

#1150000
0"
0.

#1155000
1"
1.

#1160000
0"
0.

#1165000
1"
1.

#1170000
0"
0.

#1175000
1"
1.

#1180000
0"
0.

#1185000
1"
1.

#1190000
0"
0.

#1195000
1"
1.

#1200000
0"
1$
0.
10

#1205000
1"
1.
b1 >

#1210000
0"
0.

#1215000
1"
1.
b11001 ;
b101 <
b11 >

#1220000
0"
0.

#1225000
1"
1.

#1230000
0"
0.

#1235000
1"
1.

#1240000
0"
0.

#1245000
1"
1.

#1250000
0"
0.

#1255000
1"
1.

#1260000
0"
0.

#1265000
1"
1.

#1270000
0"
0.

#1275000
1"
1.

#1280000
0"
0.

#1285000
1"
1.

#1290000
0"
0.

#1295000
1"
1.

#1300000
b101 !
0"
0$
0.
00

#1305000
1"
1.
b10 >

#1310000
0"
0.

#1315000
1"
1.
b0 >

#1320000
0"
0.

#1325000
1"
1.

#1330000
0"
0.

#1335000
1"
1.

#1340000
0"
0.

#1345000
1"
1.

#1350000
0"
0.

#1355000
1"
1.

#1360000
0"
0.

#1365000
1"
1.

#1370000
0"
0.

#1375000
1"
1.

#1380000
0"
0.

#1385000
1"
1.

#1390000
0"
0.

#1395000
1"
1.

#1400000
0"
1$
0.
10

#1405000
1"
1.
b1 >

#1410000
0"
0.

#1415000
1"
1.
b110011 ;
b110 <
b11 >

#1420000
0"
0.

#1425000
1"
1.

#1430000
0"
0.

#1435000
1"
1.

#1440000
0"
0.

#1445000
1"
1.

#1450000
0"
0.

#1455000
1"
1.

#1460000
0"
0.

#1465000
1"
1.

#1470000
0"
0.

#1475000
1"
1.

#1480000
0"
0.

#1485000
1"
1.

#1490000
0"
0.

#1495000
1"
1.

#1500000
b110 !
0"
0$
0%
0.
00
01

#1505000
1"
1.
b10 >

#1510000
0"
0.

#1515000
1"
1.
b0 >

#1520000
0"
0.

#1525000
1"
1.

#1530000
0"
0.

#1535000
1"
1.

#1540000
0"
0.

#1545000
1"
1.

#1550000
0"
0.

#1555000
1"
1.

#1560000
0"
0.

#1565000
1"
1.

#1570000
0"
0.

#1575000
1"
1.

#1580000
0"
0.

#1585000
1"
1.

#1590000
0"
0.

#1595000
1"
1.

#1600000
0"
1$
0.
10

#1605000
1"
1.
b1 >

#1610000
0"
0.

#1615000
1"
1.
b1100110 ;
b111 <
b11 >

#1620000
0"
0.

#1625000
1"
1.

#1630000
0"
0.

#1635000
1"
1.

#1640000
0"
0.

#1645000
1"
1.

#1650000
0"
0.

#1655000
1"
1.

#1660000
0"
0.

#1665000
1"
1.

#1670000
0"
0.

#1675000
1"
1.

#1680000
0"
0.

#1685000
1"
1.

#1690000
0"
0.

#1695000
1"
1.

#1700000
b111 !
0"
0$
1%
0.
00
11

#1705000
1"
1.
b10 >

#1710000
0"
0.

#1715000
1"
1.
b0 >

#1720000
0"
0.

#1725000
1"
1.

#1730000
0"
0.

#1735000
1"
1.

#1740000
0"
0.

#1745000
1"
1.

#1750000
0"
0.

#1755000
1"
1.

#1760000
0"
0.

#1765000
1"
1.

#1770000
0"
0.

#1775000
1"
1.

#1780000
0"
0.

#1785000
1"
1.

#1790000
0"
0.

#1795000
1"
1.

#1800000
0"
1$
0.
10

#1805000
1"
1.
b1 >

#1810000
0"
0.

#1815000
1"
b11001101 +
1-
1.
18
b11001101 9
b11001101 ;
b0 <
b11 >

#1820000
0"
0.

#1825000
1"
1.

#1830000
0"
0.

#1835000
1"
1.

#1840000
0"
0.

#1845000
1"
1.

#1850000
0"
0.

#1855000
1"
1.

#1860000
0"
0.

#1865000
1"
1.

#1870000
0"
0.

#1875000
1"
1.

#1880000
0"
0.

#1885000
1"
1.

#1890000
0"
0.

#1895000
1"
1.

#1900000
b1000 !
0"
0$
0%
0.
00
01

#1905000
1"
1.
b10 >

#1910000
0"
0.

#1915000
1"
1.
b0 >

#1920000
0"
0.

#1925000
1"
1.

#1930000
0"
0.

#1935000
1"
1.

#1940000
0"
0.

#1945000
1"
1.

#1950000
0"
0.

#1955000
1"
1.

#1960000
0"
0.

#1965000
1"
1.

#1970000
0"
0.

#1975000
1"
1.

#1980000
0"
0.

#1985000
1"
1.

#1990000
0"
0.

#1995000
1"
1.

#2000000
0"
1'
0.
15

#2005000
1"
0*
b0 +
0-
1.
04
08
b0 9
b0 ;

#2010000
0"
0.

#2015000
1"
1.

#2020000
0"
0.

#2025000
1"
1.

#2030000
0"
0.

#2035000
1"
1.

#2040000
0"
0.

#2045000
1"
1.

#2050000
0"
0.

#2055000
1"
1.

#2060000
0"
0.

#2065000
1"
1.

#2070000
0"
0.

#2075000
1"
1.

#2080000
0"
0.

#2085000
1"
1.

#2090000
0"
0.

#2095000
1"
1.

#2100000
0"
0'
0.
05
b1101010 @

#2105000
1"
1*
1.
14

#2110000
0"
0.

#2115000
1"
1.

#2120000
0"
0.

#2125000
1"
1.

#2130000
0"
0.

#2135000
1"
1.

#2140000
0"
0.

#2145000
1"
1.

#2150000
0"
0.

#2155000
1"
1.

#2160000
0"
0.

#2165000
1"
1.

#2170000
0"
0.

#2175000
1"
1.

#2180000
0"
0.

#2185000
1"
1.

#2190000
0"
0.

#2195000
1"
1.

#2200000
0"
1&
0.
12

#2205000
1"
1.
b1 =

#2210000
0"
0.

#2215000
1"
1.
b11 =

#2220000
0"
0.

#2225000
1"
0*
1.
04

#2230000
0"
0.

#2235000
1"
1.

#2240000
0"
0.

#2245000
1"
1.

#2250000
0"
0.

#2255000
1"
1.

#2260000
0"
0.

#2265000
1"
1.

#2270000
0"
0.

#2275000
1"
1.

#2280000
0"
0.

#2285000
1"
1.

#2290000
0"
0.

#2295000
1"
1.

#2300000
0"
b1101010 (
0.
b1101010 6

#2305000
1"
1.

#2310000
0"
0.

#2315000
1"
1.

#2320000
0"
0.

#2325000
1"
1.

#2330000
0"
0.

#2335000
1"
1.

#2340000
0"
0.

#2345000
1"
1.

#2350000
0"
0.

#2355000
1"
1.

#2360000
0"
0.

#2365000
1"
1.

#2370000
0"
0.

#2375000
1"
1.

#2380000
0"
0.

#2385000
1"
1.

#2390000
0"
0.

#2395000
1"
1.

#2400000
0"
0&
0.
02

#2405000
1"
1.
b10 =

#2410000
0"
0.

#2415000
1"
1*
1,
1.
14
17
b1101010 :
b0 =

#2420000
0"
0.

#2425000
1"
1.

#2430000
0"
0.

#2435000
1"
1.

#2440000
0"
0.

#2445000
1"
1.

#2450000
0"
0.

#2455000
1"
1.

#2460000
0"
0.

#2465000
1"
1.

#2470000
0"
0.

#2475000
1"
1.

#2480000
0"
0.

#2485000
1"
1.

#2490000
0"
0.

#2495000
1"
1.

#2500000
0"
0.
b0 ?

#2505000
1"
1.

#2510000
0"
0.

#2515000
1"
1.

#2520000
0"
0.

#2525000
1"
1.

#2530000
0"
0.

#2535000
1"
1.

#2540000
0"
0.

#2545000
1"
1.

#2550000
0"
0.

#2555000
1"
1.

#2560000
0"
0.

#2565000
1"
1.

#2570000
0"
0.

#2575000
1"
1.

#2580000
0"
0.

#2585000
1"
1.

#2590000
0"
0.

#2595000
1"
1.

#2600000
b0 !
0"
0.

#2605000
1"
1.

#2610000
0"
0.

#2615000
1"
1.

#2620000
0"
0.

#2625000
1"
1.

#2630000
0"
0.

#2635000
1"
1.

#2640000
0"
0.

#2645000
1"
1.

#2650000
0"
0.

#2655000
1"
1.

#2660000
0"
0.

#2665000
1"
1.

#2670000
0"
0.

#2675000
1"
1.

#2680000
0"
0.

#2685000
1"
1.

#2690000
0"
0.

#2695000
1"
1.

#2700000
0"
1$
0.
10

#2705000
1"
1.
b1 >

#2710000
0"
0.

#2715000
1"
1.
b1 <
b11 >

#2720000
0"
0.

#2725000
1"
1.

#2730000
0"
0.

#2735000
1"
1.

#2740000
0"
0.

#2745000
1"
1.

#2750000
0"
0.

#2755000
1"
1.

#2760000
0"
0.

#2765000
1"
1.

#2770000
0"
0.

#2775000
1"
1.

#2780000
0"
0.

#2785000
1"
1.

#2790000
0"
0.

#2795000
1"
1.

#2800000
b1 !
0"
0$
0.
00

#2805000
1"
1.
b10 >

#2810000
0"
0.

#2815000
1"
1)
0,
1.
13
07
b0 >

#2820000
0"
0.

#2825000
1"
1.

#2830000
0"
0.

#2835000
1"
1.

#2840000
0"
0.

#2845000
1"
1.

#2850000
0"
0.

#2855000
1"
1.

#2860000
0"
0.

#2865000
1"
1.

#2870000
0"
0.

#2875000
1"
1.

#2880000
0"
0.

#2885000
1"
1.

#2890000
0"
0.

#2895000
1"
1.

#2900000
0"
1$
0.
10

#2905000
1"
1.
b1 >

#2910000
0"
0.

#2915000
1"
1.
b10 <
b11 >

#2920000
0"
0.

#2925000
1"
1.

#2930000
0"
0.

#2935000
1"
1.

#2940000
0"
0.

#2945000
1"
1.

#2950000
0"
0.

#2955000
1"
1.

#2960000
0"
0.

#2965000
1"
1.

#2970000
0"
0.

#2975000
1"
1.

#2980000
0"
0.

#2985000
1"
1.

#2990000
0"
0.

#2995000
1"
1.

#3000000
b10 !
0"
0$
0.
00

#3005000
1"
1.
b10 >

#3010000
0"
0.

#3015000
1"
1.
b0 >

#3020000
0"
0.

#3025000
1"
1.

#3030000
0"
0.

#3035000
1"
1.

#3040000
0"
0.

#3045000
1"
1.

#3050000
0"
0.

#3055000
1"
1.

#3060000
0"
0.

#3065000
1"
1.

#3070000
0"
0.

#3075000
1"
1.

#3080000
0"
0.

#3085000
1"
1.

#3090000
0"
0.

#3095000
1"
1.

#3100000
0"
1$
0.
10

#3105000
1"
1.
b1 >

#3110000
0"
0.

#3115000
1"
1.
b11 <
b11 >

#3120000
0"
0.

#3125000
1"
1.

#3130000
0"
0.

#3135000
1"
1.

#3140000
0"
0.

#3145000
1"
1.

#3150000
0"
0.

#3155000
1"
1.

#3160000
0"
0.

#3165000
1"
1.

#3170000
0"
0.

#3175000
1"
1.

#3180000
0"
0.

#3185000
1"
1.

#3190000
0"
0.

#3195000
1"
1.

#3200000
b11 !
0"
0$
0.
00

#3205000
1"
1.
b10 >

#3210000
0"
0.

#3215000
1"
0)
1.
03
b0 >

#3220000
0"
0.

#3225000
1"
1.

#3230000
0"
0.

#3235000
1"
1.

#3240000
0"
0.

#3245000
1"
1.

#3250000
0"
0.

#3255000
1"
1.

#3260000
0"
0.

#3265000
1"
1.

#3270000
0"
0.

#3275000
1"
1.

#3280000
0"
0.

#3285000
1"
1.

#3290000
0"
0.

#3295000
1"
1.

#3300000
0"
1$
0.
10

#3305000
1"
1.
b1 >

#3310000
0"
0.

#3315000
1"
1.
b100 <
b11 >

#3320000
0"
0.

#3325000
1"
1.

#3330000
0"
0.

#3335000
1"
1.

#3340000
0"
0.

#3345000
1"
1.

#3350000
0"
0.

#3355000
1"
1.

#3360000
0"
0.

#3365000
1"
1.

#3370000
0"
0.

#3375000
1"
1.

#3380000
0"
0.

#3385000
1"
1.

#3390000
0"
0.

#3395000
1"
1.

#3400000
b100 !
0"
0$
0.
00

#3405000
1"
1.
b10 >

#3410000
0"
0.

#3415000
1"
1)
1.
13
b0 >

#3420000
0"
0.

#3425000
1"
1.

#3430000
0"
0.

#3435000
1"
1.

#3440000
0"
0.

#3445000
1"
1.

#3450000
0"
0.

#3455000
1"
1.

#3460000
0"
0.

#3465000
1"
1.

#3470000
0"
0.

#3475000
1"
1.

#3480000
0"
0.

#3485000
1"
1.

#3490000
0"
0.

#3495000
1"
1.

#3500000
0"
1$
0.
10

#3505000
1"
1.
b1 >

#3510000
0"
0.

#3515000
1"
1.
b101 <
b11 >

#3520000
0"
0.

#3525000
1"
1.

#3530000
0"
0.

#3535000
1"
1.

#3540000
0"
0.

#3545000
1"
1.

#3550000
0"
0.

#3555000
1"
1.

#3560000
0"
0.

#3565000
1"
1.

#3570000
0"
0.

#3575000
1"
1.

#3580000
0"
0.

#3585000
1"
1.

#3590000
0"
0.

#3595000
1"
1.

#3600000
b101 !
0"
0$
0.
00

#3605000
1"
1.
b10 >

#3610000
0"
0.

#3615000
1"
0)
1.
03
b0 >

#3620000
0"
0.

#3625000
1"
1.

#3630000
0"
0.

#3635000
1"
1.

#3640000
0"
0.

#3645000
1"
1.

#3650000
0"
0.

#3655000
1"
1.

#3660000
0"
0.

#3665000
1"
1.

#3670000
0"
0.

#3675000
1"
1.

#3680000
0"
0.

#3685000
1"
1.

#3690000
0"
0.

#3695000
1"
1.

#3700000
0"
1$
0.
10

#3705000
1"
1.
b1 >

#3710000
0"
0.

#3715000
1"
1.
b110 <
b11 >

#3720000
0"
0.

#3725000
1"
1.

#3730000
0"
0.

#3735000
1"
1.

#3740000
0"
0.

#3745000
1"
1.

#3750000
0"
0.

#3755000
1"
1.

#3760000
0"
0.

#3765000
1"
1.

#3770000
0"
0.

#3775000
1"
1.

#3780000
0"
0.

#3785000
1"
1.

#3790000
0"
0.

#3795000
1"
1.

#3800000
b110 !
0"
0$
0.
00

#3805000
1"
1.
b10 >

#3810000
0"
0.

#3815000
1"
1)
1.
13
b0 >

#3820000
0"
0.

#3825000
1"
1.

#3830000
0"
0.

#3835000
1"
1.

#3840000
0"
0.

#3845000
1"
1.

#3850000
0"
0.

#3855000
1"
1.

#3860000
0"
0.

#3865000
1"
1.

#3870000
0"
0.

#3875000
1"
1.

#3880000
0"
0.

#3885000
1"
1.

#3890000
0"
0.

#3895000
1"
1.

#3900000
0"
1$
0.
10

#3905000
1"
1.
b1 >

#3910000
0"
0.

#3915000
1"
1.
b111 <
b11 >

#3920000
0"
0.

#3925000
1"
1.

#3930000
0"
0.

#3935000
1"
1.

#3940000
0"
0.

#3945000
1"
1.

#3950000
0"
0.

#3955000
1"
1.

#3960000
0"
0.

#3965000
1"
1.

#3970000
0"
0.

#3975000
1"
1.

#3980000
0"
0.

#3985000
1"
1.

#3990000
0"
0.

#3995000
1"
1.

#4000000
b111 !
0"
0$
0.
00

#4005000
1"
1.
b10 >

#4010000
0"
0.

#4015000
1"
0)
1.
03
b0 >

#4020000
0"
0.

#4025000
1"
1.

#4030000
0"
0.

#4035000
1"
1.

#4040000
0"
0.

#4045000
1"
1.

#4050000
0"
0.

#4055000
1"
1.

#4060000
0"
0.

#4065000
1"
1.

#4070000
0"
0.

#4075000
1"
1.

#4080000
0"
0.

#4085000
1"
1.

#4090000
0"
0.

#4095000
1"
1.

#4100000
0"
1$
0.
10

#4105000
1"
1.
b1 >

#4110000
0"
0.

#4115000
1"
1-
1.
18
b0 <
b11 >

#4120000
0"
0.

